{
  "requestsFinished": 1,
  "requestsFailed": 0,
  "requestsRetries": 0,
  "requestsFailedPerMinute": 0,
  "requestsFinishedPerMinute": 6,
  "requestMinDurationMillis": 486,
  "requestMaxDurationMillis": 486,
  "requestTotalFailedDurationMillis": 0,
  "requestTotalFinishedDurationMillis": 486,
  "crawlerStartedAt": "2024-04-02T19:28:49.676Z",
  "crawlerFinishedAt": "2024-04-02T19:29:00.427Z",
  "statsPersistedAt": "2024-04-02T19:29:00.427Z",
  "crawlerRuntimeMillis": 10781,
  "crawlerLastStartTimestamp": 1712086129646,
  "requestRetryHistogram": [
    1
  ],
  "statsId": 32,
  "requestAvgFailedDurationMillis": null,
  "requestAvgFinishedDurationMillis": 486,
  "requestTotalDurationMillis": 486,
  "requestsTotal": 1,
  "requestsWithStatusCode": {},
  "errors": {},
  "retryErrors": {}
}